{
  "general": {
    "prompt_prefix": "Eres un tutor de comunicación aumentativa que habla en español latino, usa frases cortas y cálidas.",
    "fallback": "Estoy aquí para practicar tus palabras y pictogramas cuando lo necesites.",
    "greetings": [
      "¡Hola! Vamos a comunicarnos con pictogramas.",
      "¡Qué alegría verte! Dí una palabra y la practicamos juntos."
    ],
    "greeting_triggers": ["hola", "buenos dias", "buenas tardes", "buenas noches"],
    "encouragement": [
      "Excelente esfuerzo, respira profundo y seguimos.",
      "Cada pictograma que nombras te ayuda a expresar más cosas." 
    ],
    "context_hint": "Recuerda siempre usar las palabras que practicamos con tus pictogramas.",
    "related_templates": [
      "Cuando practicas {word}, también piensa en {associations}.",
      "{word} se complementa con {associations}. ¡Dilos conmigo!"
    ]
  },
  "assignment": {
    "intro_templates": [
      "Estamos trabajando en la actividad: {task}.",
      "El objetivo de hoy es usar las palabras: {words}."
    ],
    "hint_templates": [
      "Observa el pictograma de {word} y menciona para qué lo usas.",
      "Piensa en una situación donde digas {word} y cuéntamela." 
    ]
  },
  "guided_session": {
    "intro": "Esta sesión guiada necesita practicar la palabra {word} con calma.",
    "success": [
      "¡Muy bien! Cambiemos a la siguiente tarjeta.",
      "¡Excelente pronunciación! Seguimos con otra palabra." 
    ],
    "hint": "La palabra comienza con {clue}"
  },
  "related_vocab": {
    "caballo": ["heno", "galopar", "herradura", "establo"],
    "elefante": ["trompa", "manada", "agua"],
    "rinoceronte": ["cuerno", "savana", "pesado"],
    "sapo": ["charco", "verde", "croar"],
    "ardilla": ["arbol", "nuez", "cola"],
    "perro": ["correa", "ladrido", "pelota"],
    "gato": ["maullar", "bigotes", "suave"],
    "pajaro": ["alas", "volar", "nido"],
    "pez": ["agua", "nadar", "pecera"],
    "oso": ["invierno", "abrazo", "grande"],
    "leon": ["melena", "selva", "rugido"],
    "manzana": ["roja", "crujiente", "merienda", "jugo"],
    "banana": ["amarilla", "dulce", "pelar"],
    "pan": ["tostada", "mantequilla", "horno"],
    "leche": ["vaso", "desayuno", "calcio"],
    "agua": ["vaso", "sed", "fresca"],
    "galleta": ["dulce", "caja", "merienda"],
    "arroz": ["plato", "blanco", "cena"],
    "sopa": ["caliente", "cuchara", "tazon"],
    "pizza": ["queso", "rebanada", "horno"],
    "audifonos": ["musica", "oidos", "escuchar"],
    "telefono": ["llamada", "mensaje", "pantalla"],
    "tablet": ["tocar", "aplicacion", "juego"],
    "anillo": ["mano", "brilla", "regalo"],
    "libro": ["leer", "paginas", "historia"],
    "cuaderno": ["notas", "tareas", "lineas"],
    "lapiz": ["escribir", "borrar", "afilado"],
    "mochila": ["escuela", "cargar", "bolsillo"],
    "pelota": ["rebotar", "juego", "cancha"],
    "parque": ["columpio", "resbaladilla", "amigos"],
    "casa": ["familia", "sala", "hogar"],
    "escuela": ["maestra", "clase", "recreo"],
    "hospital": ["doctor", "ambulancia", "cuidar"],
    "ambulancia": ["sirena", "emergencia", "hospital"],
    "autobus": ["ruta", "asientos", "chofer"],
    "auto": ["ruedas", "cinturon", "viaje"],
    "bicicleta": ["pedalear", "casco", "parque"],
    "avion": ["alas", "nubes", "viajar"],
    "tren": ["viaje", "vagon", "anden"],
    "semaforo": ["luz", "cruzar", "seguridad"],
    "pictograma": ["secuencia", "tablero", "expresar"],
    "mama": ["abrazo", "cariño", "casa"],
    "papa": ["fuerte", "guiar", "jugar"],
    "hermano": ["compartir", "jugar", "familia"],
    "hermana": ["risas", "apoyo", "familia"],
    "abuelo": ["historias", "paciencia", "cafe"],
    "abuela": ["cocina", "abrazo", "consejo"],
    "amigo": ["juego", "confianza", "risas"],
    "feliz": ["sonrisa", "abrazo", "cancion"],
    "triste": ["llorar", "consuelo", "respirar"],
    "enojado": ["respirar", "contar", "calma"],
    "calmado": ["respirar", "susurro", "descanso"],
    "miedo": ["apoyo", "mano", "luz"],
    "cansado": ["descanso", "dormir", "silencio"],
    "dormir": ["sabanas", "sueños", "noche"],
    "comer": ["tenedor", "plato", "familia"],
    "cepillar": ["dientes", "pasta", "bano"],
    "banar": ["agua", "jabon", "toalla"],
    "jugar": ["turnos", "reglas", "risas"],
    "correr": ["rapido", "aire", "ejercicio"],
    "saltar": ["trampolin", "piernas", "energia"],
    "cantar": ["melodia", "voz", "ritmo"],
    "bailar": ["musica", "pasos", "ritmo"],
    "colores": ["rojo", "azul", "amarillo"],
    "rojo": ["fuego", "corazon", "stop"],
    "azul": ["cielo", "agua", "calma"],
    "verde": ["hojas", "esperanza", "semaforo"],
    "amarillo": ["sol", "sonrisa", "luz"],
    "numero": ["contar", "sumar", "juego"],
    "uno": ["primero", "dedo", "inicio"],
    "dos": ["pareja", "ojos", "manos"],
    "tres": ["pasos", "amigos", "trio"],
    "rabano": ["huerto", "ensalada", "crujiente"],
    "extraterrestre": ["planetas", "nave", "amistad"]
  },
  "scenarios": [
    {
      "id": "rutina_salir_casa",
      "intents": ["rutina_escolar"],
      "triggers": [
        "antes de salir",
        "salir de casa",
        "antes de ir a la escuela"
      ],
      "response": "Antes de salir de casa repasemos estos pasos:",
      "steps": [
        "Guarda cuadernos y estuche dentro de la mochila.",
        "Coloca la botella de agua o lonchera en el bolsillo frontal.",
        "Respira profundo y elige el pictograma que muestra cómo te sientes."
      ],
      "follow_up": "Cuando termines me cuentas y celebramos tu rutina.",
      "pictogram_keyword": "mochila",
      "dynamic_steps": true,
      "tone": "calmo"
    },
    {
      "id": "terapia_practicar_sonido",
      "intents": ["terapia_habla"],
      "triggers": [
        "terapia del habla",
        "practicar sonido",
        "pronunciar",
        "sonido dificil"
      ],
      "response": "Practiquemos el sonido con calma:",
      "steps": [
        "Inhala por la nariz y cuenta tres.",
        "Mira el pictograma de la boca abierta para recordar la forma.",
        "Di el sonido tres veces y aplaude cuando lo logres."
      ],
      "follow_up": "Si te cansas, toma agua y seguimos cuando digas.",
      "pictogram_keyword": "hablar",
      "dynamic_steps": true,
      "tone": "calmo"
    },
    {
      "id": "juego_cooperativo_memoria",
      "intents": ["juego_cooperativo", "juego_pista"],
      "triggers": [
        "juego cooperativo",
        "juego de memoria",
        "jugar memoria"
      ],
      "response": "En el juego cooperativo recuerda:",
      "steps": [
        "Observa dos tarjetas y nombra lo que ves.",
        "Espera tu turno diciendo 'ahora tú'.",
        "Si te frustras, toca el pictograma de calma y respira."
      ],
      "follow_up": "Dime qué parejas encontraste para celebrarlo.",
      "pictogram_keyword": "jugar",
      "tone": "emocionado"
    },
    {
      "id": "autonomia_lavar_manos",
      "intents": ["autonomia_diaria"],
      "triggers": [
        "lavarme las manos",
        "higiene",
        "antes de comer"
      ],
      "response": "Lavemos las manos paso a paso:",
      "steps": [
        "Abre el grifo y moja las manos.",
        "Frota con jabón contando hasta diez.",
        "Enjuaga, seca y muestra el pictograma de manos limpias."
      ],
      "follow_up": "Cuando termines puedes elegir el pictograma de 'listo'.",
      "pictogram_keyword": "agua",
      "dynamic_steps": true,
      "tone": "calmo"
    },
    {
      "id": "concepto_color_cielo",
      "intents": ["factual_pregunta"],
      "triggers": [
        "color es el cielo",
        "color del cielo",
        "cielo de que color"
      ],
      "response": "Durante el día el cielo casi siempre es azul clarito con nubes blancas.",
      "follow_up": "Busca el pictograma de azul o de nube para mostrarlo.",
      "pictogram_keyword": "azul"
    }
  ]
}
